README.rst
setup.py
microasync/__init__.py
microasync/async.py
microasync/device.py
microasync/utils.py
microasync.egg-info/PKG-INFO
microasync.egg-info/SOURCES.txt
microasync.egg-info/dependency_links.txt
microasync.egg-info/top_level.txt