Metadata-Version: 1.0
Name: microasync
Version: 0.3
Summary: Green threads and CSP for micropython.
Home-page: https://github.com/nvbn/microasync/
Author: Vladimir Iakovlev
Author-email: nvbn.rm@gmail.com
License: MIT
Platform: UNKNOWN
